django_rest_framework_angular_resource_generator-0.7.0.dist-info/DESCRIPTION.rst
django_rest_framework_angular_resource_generator-0.7.0.dist-info/METADATA
django_rest_framework_angular_resource_generator-0.7.0.dist-info/RECORD
django_rest_framework_angular_resource_generator-0.7.0.dist-info/WHEEL
django_rest_framework_angular_resource_generator-0.7.0.dist-info/metadata.json
django_rest_framework_angular_resource_generator-0.7.0.dist-info/top_level.txt
drf_ng_generator/__init__.py
drf_ng_generator/converter.py
drf_ng_generator/schemas.py
drf_ng_generator/management/__init__.py
drf_ng_generator/management/commands/__init__.py
drf_ng_generator/management/commands/drf_ng.py
drf_ng_generator/templates/ngResource.coffee
drf_ng_generator/templates/ngResource.js
