Metadata-Version: 2.0
Name: django-rest-framework-angular-resource-generator
Version: 0.7.0
Summary: Angular resource generator for DRF
Home-page: UNKNOWN
Author: Gerasev Kirill
Author-email: gerasev.kirill@gmail.com
License: BSD License
Platform: UNKNOWN
Classifier: Environment :: Web Environment
Classifier: Framework :: Django
Classifier: Intended Audience :: Developers
Classifier: License :: OSI Approved :: BSD License
Classifier: Operating System :: OS Independent
Classifier: Programming Language :: Python
Classifier: Programming Language :: Python :: 2.7
Classifier: Topic :: Internet :: WWW/HTTP
Classifier: Topic :: Internet :: WWW/HTTP :: Dynamic Content
Requires-Dist: coreapi
Requires-Dist: djangorestframework
